stealthflow/__init__.py
stealthflow/fid.py
stealthflow/resnest.py
stealthflow/tf_layers.py
StealthFlow-0.0.13.dist-info/LICENSE
StealthFlow-0.0.13.dist-info/METADATA
StealthFlow-0.0.13.dist-info/WHEEL
StealthFlow-0.0.13.dist-info/top_level.txt
StealthFlow-0.0.13.dist-info/RECORD
